LICENSE
README.md
pyproject.toml
setup.py
elements_frameioclient.egg-info/PKG-INFO
elements_frameioclient.egg-info/SOURCES.txt
elements_frameioclient.egg-info/dependency_links.txt
elements_frameioclient.egg-info/entry_points.txt
elements_frameioclient.egg-info/requires.txt
elements_frameioclient.egg-info/top_level.txt
frameioclient/__init__.py
frameioclient/client.py
frameioclient/config.py
frameioclient/fiocli.py
frameioclient/lib/__init__.py
frameioclient/lib/bandwidth.py
frameioclient/lib/constants.py
frameioclient/lib/download.py
frameioclient/lib/exceptions.py
frameioclient/lib/logger.py
frameioclient/lib/service.py
frameioclient/lib/telemetry.py
frameioclient/lib/transfer.py
frameioclient/lib/transport.py
frameioclient/lib/upload.py
frameioclient/lib/utils.py
frameioclient/lib/version.py
frameioclient/services/__init__.py
frameioclient/services/assets.py
frameioclient/services/comments.py
frameioclient/services/helpers.py
frameioclient/services/links.py
frameioclient/services/logs.py
frameioclient/services/projects.py
frameioclient/services/search.py
frameioclient/services/teams.py
frameioclient/services/users.py
scripts/__init__.py
scripts/benchmark/__init__.py
scripts/benchmark/download.py
scripts/benchmark/upload.py
scripts/benchmark/utils.py
tests/test_frameioclient.py
tests/test_frameiodownloader.py