Metadata-Version: 2.1
Name: elements-frameioclient
Version: 2.0.0
Summary: Client library for the Frame.io API
Home-page: https://github.com/frameio/python-frameio-client
Author: Frame.io, Inc.
Author-email: platform@frame.io
License: MIT
Classifier: Development Status :: 5 - Production/Stable
Classifier: Intended Audience :: Developers
Classifier: Topic :: Multimedia :: Video
Classifier: Topic :: Software Development :: Libraries
Classifier: License :: OSI Approved :: MIT License
Classifier: Programming Language :: Python :: 3.6
Classifier: Programming Language :: Python :: 3.7
Classifier: Programming Language :: Python :: 3.8
Classifier: Programming Language :: Python :: 3.9
Requires-Python: >=3.6.5, <4
Provides-Extra: dev
License-File: LICENSE
